DBConnectionPool/__init__.py
DBConnectionPool/database.py
DBConnectionPool/interfaces.py
DBConnectionPool/sql.py
DBConnectionPool/testconn.py
dbconnectionpool-0.3.2.dist-info/licenses/LICENSE
dbconnectionpool-0.3.2.dist-info/METADATA
dbconnectionpool-0.3.2.dist-info/WHEEL
dbconnectionpool-0.3.2.dist-info/entry_points.txt
dbconnectionpool-0.3.2.dist-info/top_level.txt
dbconnectionpool-0.3.2.dist-info/RECORD
