Metadata-Version: 2.4
Name: DBConnectionPool
Version: 0.3.2
Summary: A simple connection pool library.
Author: Erri4
License: Copyright © Erri4, 2025
Project-URL: Homepage, https://github.com/erri4/DBConnectionPool
Project-URL: Bug Tracker, https://github.com/erri4/DBConnectionPool/issues
Classifier: License :: Other/Proprietary License
Requires-Python: >=3.8
License-File: LICENSE
Requires-Dist: PyMySQL
Requires-Dist: dbutils
Dynamic: license-file
